datasette_unsafe_expose_env/__init__.py
datasette_unsafe_expose_env-0.1.1.dist-info/METADATA
datasette_unsafe_expose_env-0.1.1.dist-info/WHEEL
datasette_unsafe_expose_env-0.1.1.dist-info/entry_points.txt
datasette_unsafe_expose_env-0.1.1.dist-info/top_level.txt
datasette_unsafe_expose_env-0.1.1.dist-info/RECORD
