Metadata-Version: 2.1
Name: datasette-unsafe-expose-env
Version: 0.1.1
Summary: Datasette plugin to expose some environment variables at /-/env for debugging
Home-page: https://github.com/simonw/datasette-unsafe-expose-env
Author: Simon Willison
License: Apache License, Version 2.0
Project-URL: Issues, https://github.com/simonw/datasette-unsafe-expose-env/issues
Project-URL: CI, https://github.com/simonw/datasette-unsafe-expose-env/actions
Project-URL: Changelog, https://github.com/simonw/datasette-unsafe-expose-env/releases
Requires-Python: >=3.6
Requires-Dist: datasette
Provides-Extra: test
Requires-Dist: pytest ; extra == 'test'
Requires-Dist: pytest-asyncio ; extra == 'test'
